dezerogym/__init__.py
dezerogym/gridworld.py
dezerogym/gridworld_render.py
dezerogym-0.0.0.dist-info/LICENSE.md
dezerogym-0.0.0.dist-info/METADATA
dezerogym-0.0.0.dist-info/WHEEL
dezerogym-0.0.0.dist-info/top_level.txt
dezerogym-0.0.0.dist-info/RECORD
