Metadata-Version: 2.1
Name: dezerogym
Version: 0.0.0
Summary: Reinforcement learning environment used in the book "Deep Learning from Scratch 4"
Home-page: UNKNOWN
Author: Koki Saitoh
Author-email: koki0702@gmail.com
License: MIT License
Platform: UNKNOWN
Requires-Dist: numpy
Requires-Dist: matplotlib
